<?xml version = '1.0' encoding = 'UTF-8'?>
<Relation class="oracle.dbtools.crest.model.design.logical.Relation" name="FK_MANAGERS_ARTISTS" directorySegmentName="seg_0" id="9AB2F6A3-098A-AC8F-3E14-0595EE2094B9">
<createdBy>angelowu</createdBy>
<createdTime>2023-02-23 00:11:00 UTC</createdTime>
<ownerDesignName>enterprise</ownerDesignName>
<engineerTo>
<item key="01B4F61A-73CF-165C-B10C-BC8ED0BEBA84" value="true"/>
</engineerTo>
<identifying>false</identifying>
<optionalSource>false</optionalSource>
<optionalTarget>false</optionalTarget>
<sourceCardinality>1</sourceCardinality>
<sourceEntity>476C07AC-7E09-968A-F7AA-4DD2663D2266</sourceEntity>
<targetCardinalityString>*</targetCardinalityString>
<targetEntity>168C64A2-5B11-A473-8D6A-56E52761E734</targetEntity>
<transferable>true</transferable>
<deleteRule>NO ACTION</deleteRule>
</Relation>